CHANGES.txt
CONTRIBUTORS.txt
MANIFEST.in
README.txt
setup.cfg
setup.py
collective/__init__.py
collective.atspreadsheet.egg-info/PKG-INFO
collective.atspreadsheet.egg-info/SOURCES.txt
collective.atspreadsheet.egg-info/dependency_links.txt
collective.atspreadsheet.egg-info/entry_points.txt
collective.atspreadsheet.egg-info/namespace_packages.txt
collective.atspreadsheet.egg-info/not-zip-safe
collective.atspreadsheet.egg-info/paster_plugins.txt
collective.atspreadsheet.egg-info/requires.txt
collective.atspreadsheet.egg-info/top_level.txt
collective/atspreadsheet/README.txt
collective/atspreadsheet/__init__.py
collective/atspreadsheet/config.py
collective/atspreadsheet/configure.zcml
collective/atspreadsheet/skins.zcml
collective/atspreadsheet/subscribers.py
collective/atspreadsheet/widget.py
collective/atspreadsheet/browser/__init__.py
collective/atspreadsheet/browser/configure.zcml
collective/atspreadsheet/content/__init__.py
collective/atspreadsheet/content/configure.zcml
collective/atspreadsheet/content/csvspreadsheet.py
collective/atspreadsheet/content/spreadsheet.py
collective/atspreadsheet/interfaces/__init__.py
collective/atspreadsheet/interfaces/csvspreadsheet.py
collective/atspreadsheet/interfaces/spreadsheet.py
collective/atspreadsheet/locales/collective.atspreadsheet-manual.pot
collective/atspreadsheet/locales/collective.atspreadsheet.pot
collective/atspreadsheet/portlets/__init__.py
collective/atspreadsheet/portlets/configure.zcml
collective/atspreadsheet/profiles/default/factorytool.xml
collective/atspreadsheet/profiles/default/metadata.xml
collective/atspreadsheet/profiles/default/portlets.xml
collective/atspreadsheet/profiles/default/rolemap.xml
collective/atspreadsheet/profiles/default/skins.xml
collective/atspreadsheet/profiles/default/types.xml
collective/atspreadsheet/profiles/default/types/CSVSpreadsheet.xml
collective/atspreadsheet/profiles/default/types/Spreadsheet.xml
collective/atspreadsheet/skins/collective_atspreadsheet/arrow_refresh.png
collective/atspreadsheet/skins/collective_atspreadsheet/disk.png
collective/atspreadsheet/skins/collective_atspreadsheet/find.png
collective/atspreadsheet/skins/collective_atspreadsheet/jgcharts.min.js
collective/atspreadsheet/skins/collective_atspreadsheet/jquery-1.4.2.min.js
collective/atspreadsheet/skins/collective_atspreadsheet/jquery-ui-1.8.custom.css
collective/atspreadsheet/skins/collective_atspreadsheet/jquery-ui-1.8.custom.min.js
