Metadata-Version: 1.0
Name: collective.atspreadsheet
Version: 1.0a2
Summary: Spreadsheet content type for Plone
Home-page: http://svn.plone.org/svn/collective/
Author: Izhar Firdaus
Author-email: izhar@inigo-tech.com
License: GPL
Keywords: spreadsheet plone content
Platform: UNKNOWN
Classifier: Framework :: Plone
Classifier: Intended Audience :: Developers
Classifier: License :: OSI Approved :: GNU General Public License (GPL)
